{
  "settings": {
    "typography": {
      "customFontSize": true,
			"dropCap": true,
			"fluid": true,
			"fontStyle": true,
			"fontWeight": true,
			"letterSpacing": true,
			"lineHeight": true,
			"textDecoration": true,
			"textTransform": true,
      "fontFamilies": [
        {
          "fontFamily": "biblio, YakuHanJPs, \"-apple-system\", \"BlinkMacSystemFont\", \"Roboto\", \"Segoe UI\", 'Hiragino Kaku Gothic ProN','Biblio Hiragino Sans', 'Noto Sans JP', 'Yu Gothic Medium', '游ゴシック Medium', 'Meiryo',  sans-serif",
          "slug": "system-gothic",
          "name": "Gothic"
        },
				{
          "fontFamily": "biblio, \"-apple-system\", \"BlinkMacSystemFont\", \"Roboto\", \"Segoe UI\", 'Hiragino Kaku Gothic ProN','Biblio Hiragino Sans', 'Noto Sans JP', 'Yu Gothic Medium', '游ゴシック Medium', 'Meiryo',  sans-serif",
          "slug": "system-gothic-vertical",
          "name": "Gothic vertical"
        },
				{
          "fontFamily": "biblio, YakuHanMPs, Times New Roman, 'ヒラギノ明朝 ProN W3', Hiragino Mincho ProN, '游明朝 Medium', 'YuMincho Medium', Noto Serif Japanese,'ヒラギノ明朝 ProN W3',Hiragino Mincho ProN, serif",
          "slug": "system-mincho",
          "name": "Mincho"
        },
				{
          "fontFamily": "biblio, Times New Roman, 'ヒラギノ明朝 ProN W3', Hiragino Mincho ProN, '游明朝 Medium', 'YuMincho Medium', Noto Serif Japanese,'ヒラギノ明朝 ProN W3',Hiragino Mincho ProN, serif",
          "slug": "system-mincho-vertical",
          "name": "Mincho vertical"
        }
      ],
			"fontSizes": [
				{
					"fluid": false,
					"size": "0.625rem",
					"slug": "xxxs",
					"name": "3XS"
				},
				{
					"fluid": false,
					"size": "0.75rem",
					"slug": "xxs",
					"name": "XXS"
				},
				{
					"fluid": false,
					"size": "0.875rem",
					"slug": "xs",
					"name": "XS"
				},
				{
					"size": "1rem",
					"fluid": {
						"min": "0.875rem",
						"max": "1rem"
					},
					"slug": "sm",
					"name": "S"
				},
				{
					"size": "1.125rem",
					"fluid": {
						"min": "1rem",
						"max": "1.125rem"
					},
					"slug": "md",
					"name": "M"
				},
				{
					"size": "1.5rem",
					"fluid": {
						"min": "1.25rem",
						"max": "1.5rem"
					},
					"slug": "lg",
					"name": "L"
				},
				{
					"size": "2rem",
					"fluid": {
						"min": "1.5rem",
						"max": "2rem"
					},
					"slug": "xl",
					"name": "XL"
				},
				{
					"size": "3rem",
					"fluid": {
						"min": "2rem",
						"max": "3rem"
					},
					"slug": "xxl",
					"name": "XXL"
				},
				{
					"fluid": false,
					"size": "calc(var(--wp--preset--font-size--xxl) * var(--wp--custom--font-size--ratio))",
					"slug": "xxxl",
					"name": "3XL"
				},
				{
					"fluid": false,
					"size": "calc(var(--wp--preset--font-size--xxxl) * var(--wp--custom--font-size--ratio))",
					"slug": "xxxxl",
					"name": "4XL"
				}
			]
    },
		"custom": {
			"fontSize": {
				"ratio": "1.5"
			}
		}
  }
}
